{"text": "Laupäeval möödub 50 aastat raadiojaama Ameerika Hääl Eestisse suunatud saadete alustamisest , esimene saade oli eetris 1951. aasta 2. juuni hommikul , kirjutas Postimees .\nAmeerika Hääle esimeses eestikeelses saates räägiti maailma sündmustest , selles oli ka ühe Ameerika Ühendriikide tollase tipp-poliitiku läkitus Eesti kuulajatele , et Ühendriigid ei tunnusta kunagi Nõukogude Liidu okupatsiooni Eestis .\n", "meta": {"file": "aja-eesti_EPL_2001_06_02_2"}, "layers": [{"name": "brat_entities", "attributes": ["brat_id"], "parent": null, "enveloping": null, "ambiguous": false, "serialisation_module": null, "meta": {}, "spans": [{"base_span": [0, 9], "annotations": [{"brat_id": "T1"}]}, {"base_span": [10, 16], "annotations": [{"brat_id": "T6"}]}, {"base_span": [17, 26], "annotations": [{"brat_id": "T2"}]}, {"base_span": [79, 91], "annotations": [{"brat_id": "T5"}]}, {"base_span": [108, 111], "annotations": [{"brat_id": "T4"}]}, {"base_span": [112, 118], "annotations": [{"brat_id": "T4"}]}, {"base_span": [119, 148], "annotations": [{"brat_id": "T3"}]}]}, {"name": "entities", "attributes": ["brat_id"], "parent": null, "enveloping": "brat_entities", "ambiguous": false, "serialisation_module": null, "meta": {}, "spans": []}, {"name": "event_arguments", "attributes": ["brat_id", "a_text", "rel_type", "b_text", "b_index"], "parent": null, "enveloping": "brat_entities", "ambiguous": true, "serialisation_module": null, "meta": {}, "spans": []}, {"name": "events", "attributes": ["brat_id", "class", "class_confidence", "duration", "duration_confidence", "comment"], "parent": null, "enveloping": "brat_entities", "ambiguous": false, "serialisation_module": null, "meta": {}, "spans": [{"base_span": [[10, 16]], "annotations": [{"brat_id": "T6", "class": "OCCURRENCE", "class_confidence": "high", "duration": "seconds", "duration_confidence": "neutral", "comment": null}]}, {"base_span": [[79, 91]], "annotations": [{"brat_id": "T5", "class": "OCCURRENCE", "class_confidence": "high", "duration": "seconds", "duration_confidence": "neutral", "comment": null}]}, {"base_span": [[108, 111], [112, 118]], "annotations": [{"brat_id": "T4", "class": "STATE", "class_confidence": "high", "duration": "minutes", "duration_confidence": "neutral", "comment": null}]}]}, {"name": "timexes", "attributes": ["brat_id", "tid", "type", "value", "mod", "anchor_time_id", "comment"], "parent": null, "enveloping": "brat_entities", "ambiguous": false, "serialisation_module": null, "meta": {}, "spans": [{"base_span": [[0, 9]], "annotations": [{"brat_id": "T1", "tid": "t1", "type": "DATE", "value": "2001-06-02", "mod": null, "anchor_time_id": null, "comment": null}]}, {"base_span": [[17, 26]], "annotations": [{"brat_id": "T2", "tid": "t2", "type": "DURATION", "value": "P50Y", "mod": null, "anchor_time_id": null, "comment": null}]}, {"base_span": [[119, 148]], "annotations": [{"brat_id": "T3", "tid": "t3", "type": "TIME", "value": "1951-06-02TMO", "mod": null, "anchor_time_id": null, "comment": null}]}]}, {"name": "tlinks", "attributes": ["brat_id", "a_text", "rel_type", "b_text", "b_index"], "parent": null, "enveloping": "brat_entities", "ambiguous": true, "serialisation_module": null, "meta": {}, "spans": [{"base_span": [[0, 9], [10, 16]], "annotations": [{"brat_id": "R2", "a_text": "Laupäeval", "rel_type": "INCLUDES", "b_text": "möödub", "b_index": 1}]}, {"base_span": [[17, 26], [79, 91]], "annotations": [{"brat_id": "R3", "a_text": "50 aastat", "rel_type": "AFTER", "b_text": "alustamisest", "b_index": 1}]}, {"base_span": [[108, 111], [112, 118], [119, 148]], "annotations": [{"brat_id": "R1", "a_text": "oli eetris", "rel_type": "IS_INCLUDED", "b_text": "1951. aasta 2. juuni hommikul", "b_index": 2}]}]}]}